MANIFEST.in
README.md
setup.py
thumbor_distributed_collage_filter/__init__.py
thumbor_distributed_collage_filter/filter.py
thumbor_distributed_collage_filter/version.py
thumbor_distributed_collage_filter.egg-info/PKG-INFO
thumbor_distributed_collage_filter.egg-info/SOURCES.txt
thumbor_distributed_collage_filter.egg-info/dependency_links.txt
thumbor_distributed_collage_filter.egg-info/entry_points.txt
thumbor_distributed_collage_filter.egg-info/requires.txt
thumbor_distributed_collage_filter.egg-info/top_level.txt