Metadata-Version: 1.1
Name: thumbor-distributed-collage-filter
Version: 0.1.0
Summary: Distributed collage is a filter for creating side-by-side images.
Home-page: https://github.com/globocom/thumbor-distributed-collage-filter
Author: Globo.com
Author-email: thumbor@corp.globo.com
License: MIT
Keywords: thumbor filter
Platform: UNKNOWN
Classifier: Development Status :: 4 - Beta
Classifier: Intended Audience :: Developers
Classifier: License :: OSI Approved :: MIT License
Classifier: Natural Language :: English
Classifier: Operating System :: Unix
Classifier: Programming Language :: Python :: 2.7
Classifier: Operating System :: OS Independent
